pearsonr/__init__.py
pearsonr/beta.py
pearsonr/main.py
pearsonr-0.1.0.dist-info/LICENSE
pearsonr-0.1.0.dist-info/METADATA
pearsonr-0.1.0.dist-info/WHEEL
pearsonr-0.1.0.dist-info/top_level.txt
pearsonr-0.1.0.dist-info/RECORD
