Metadata-Version: 2.1
Name: pearsonr
Version: 0.1.0
Summary: UNKNOWN
Home-page: https://github.com/rkhullar/pearsonr-pure-python
Author: Rajan Khullar
Author-email: rkhullar03@gmail.com
License: MIT
Keywords: pearsonr
Platform: UNKNOWN
Requires-Python: ~=3.6
